bonesis/__init__.py
bonesis/aeon.py
bonesis/asp_encoding.py
bonesis/cli.py
bonesis/debug.py
bonesis/domains.py
bonesis/language.py
bonesis/manager.py
bonesis/reprogramming.py
bonesis/snippets.py
bonesis/utils.py
bonesis/views.py
bonesis-0.6.8.1.dist-info/licenses/LICENSE.txt
bonesis-0.6.8.1.dist-info/licenses/Licence_CeCILL_V2.1-fr.txt
bonesis0/__init__.py
bonesis0/asp_encoding.py
bonesis0/clingo_solving.py
bonesis0/diversity.py
bonesis0/gil_utils.py
bonesis0/proxy_control.py
bonesis0/subset_portfolio.cfg
bonesis-0.6.8.1.dist-info/METADATA
bonesis-0.6.8.1.dist-info/WHEEL
bonesis-0.6.8.1.dist-info/entry_points.txt
bonesis-0.6.8.1.dist-info/top_level.txt
bonesis-0.6.8.1.dist-info/RECORD
