Metadata-Version: 2.4
Name: bonesis
Version: 0.6.8.1
Summary: Synthesis of Most Permissive Boolean Networks
Keywords: computational systems biology
Classifier: Intended Audience :: Science/Research
Classifier: Topic :: Scientific/Engineering :: Bio-Informatics
License-File: LICENSE.txt
License-File: Licence_CeCILL_V2.1-fr.txt
Requires-Dist: boolean.py
Requires-Dist: clingo>=5.5
Requires-Dist: colomoto_jupyter
Requires-Dist: mpbn>=3.3
Requires-Dist: networkx
Requires-Dist: numpy
Requires-Dist: pandas
Requires-Dist: scipy
Dynamic: classifier
Dynamic: keywords
Dynamic: license-file
Dynamic: requires-dist
Dynamic: summary
